FastMBAR/__init__.py
FastMBAR/fastmbar.py
FastMBAR/test_FastMBAR.py
FastMBAR/utils/analyzer.py
FastMBAR/utils/fastmbartools.py
fastmbar-1.4.6.dist-info/METADATA
fastmbar-1.4.6.dist-info/WHEEL
fastmbar-1.4.6.dist-info/licenses/LICENSE
fastmbar-1.4.6.dist-info/RECORD
