Metadata-Version: 2.3
Name: FastMBAR
Version: 1.4.6
Summary: A fast solver for large scale MBAR/UWHAM equations
Project-URL: Homepage, https://fastmbar.readthedocs.io
Project-URL: Bug Tracker, https://github.com/BrooksResearchGroup-UM/FastMBAR/issues
Author-email: Xinqiang Ding <Xinqiang.Ding@tufts.edu>
License: MIT License
License-File: LICENSE
Classifier: License :: OSI Approved :: MIT License
Classifier: Operating System :: OS Independent
Classifier: Programming Language :: Python :: 3
Requires-Python: >=3.8
Requires-Dist: numpy>=1.20.0
Requires-Dist: pytest>=7.4.0
Requires-Dist: scipy>=1.11.0
Requires-Dist: torch>=2.0.0
